LICENSE
README.md
nosql_schema_check/model.py
nosql_schema_check-0.0.8.dist-info/METADATA
nosql_schema_check-0.0.8.dist-info/WHEEL
nosql_schema_check-0.0.8.dist-info/licenses/LICENSE
nosql_schema_check-0.0.8.dist-info/RECORD
