Metadata-Version: 2.4
Name: NoSQL-Schema-Check
Version: 0.0.8
Summary: Simple package to check schema of NoSQL database (MongoDB).
Project-URL: Homepage, https://github.com/putterPatcher/NoSQL_Schema_Check
Project-URL: Issues, https://github.com/putterPatcher/NoSQL_Schema_Check/issues
Author-email: Kor Shantanu Nitin <korshantanu@gmail.com>
License: MIT
License-File: LICENSE
Classifier: Operating System :: OS Independent
Classifier: Programming Language :: Python :: 3
Requires-Python: >=3.8
Requires-Dist: flask
